tensorbite/D1.py
tensorbite/D3.py
tensorbite/D4.py
tensorbite/D5.py
tensorbite/D7.py
tensorbite/D8.py
tensorbite/M1.py
tensorbite/M2.py
tensorbite/M3.py
tensorbite/M6.py
tensorbite/M7.py
tensorbite/M8.py
tensorbite/__init__.py
tensorbite/core.py
tensorbite-0.1.dist-info/licenses/LICENSE.txt
tensorbite-0.1.dist-info/METADATA
tensorbite-0.1.dist-info/WHEEL
tensorbite-0.1.dist-info/top_level.txt
tensorbite-0.1.dist-info/RECORD
